google_cloud_aiplatform-1.133.0-py3.10-nspkg.pth
google/cloud/aiplatform/__init__.py
google/cloud/aiplatform/_publisher_models.py
google/cloud/aiplatform/_streaming_prediction.py
google/cloud/aiplatform/base.py
google/cloud/aiplatform/gapic_version.py
google/cloud/aiplatform/hyperparameter_tuning.py
google/cloud/aiplatform/initializer.py
google/cloud/aiplatform/jobs.py
google/cloud/aiplatform/models.py
google/cloud/aiplatform/persistent_resource.py
google/cloud/aiplatform/pipeline_job_schedules.py
google/cloud/aiplatform/pipeline_jobs.py
google/cloud/aiplatform/py.typed
google/cloud/aiplatform/schedules.py
google/cloud/aiplatform/schema.py
google/cloud/aiplatform/telemetry.py
google/cloud/aiplatform/training_jobs.py
google/cloud/aiplatform/version.py
google/cloud/aiplatform/_mlflow_plugin/__init__.py
google/cloud/aiplatform/_mlflow_plugin/_vertex_mlflow_tracking.py
google/cloud/aiplatform/_pipeline_based_service/__init__.py
google/cloud/aiplatform/_pipeline_based_service/pipeline_based_service.py
google/cloud/aiplatform/compat/__init__.py
google/cloud/aiplatform/compat/services/__init__.py
google/cloud/aiplatform/compat/types/__init__.py
google/cloud/aiplatform/constants/__init__.py
google/cloud/aiplatform/constants/base.py
google/cloud/aiplatform/constants/pipeline.py
google/cloud/aiplatform/constants/prediction.py
google/cloud/aiplatform/constants/schedule.py
google/cloud/aiplatform/datasets/__init__.py
google/cloud/aiplatform/datasets/_datasources.py
google/cloud/aiplatform/datasets/column_names_dataset.py
google/cloud/aiplatform/datasets/dataset.py
google/cloud/aiplatform/datasets/image_dataset.py
google/cloud/aiplatform/datasets/tabular_dataset.py
google/cloud/aiplatform/datasets/text_dataset.py
google/cloud/aiplatform/datasets/time_series_dataset.py
google/cloud/aiplatform/datasets/video_dataset.py
google/cloud/aiplatform/docker_utils/__init__.py
google/cloud/aiplatform/docker_utils/build.py
google/cloud/aiplatform/docker_utils/errors.py
google_cloud_aiplatform-1.133.0.dist-info/licenses/LICENSE
google_cloud_aiplatform-1.133.0.dist-info/METADATA
google_cloud_aiplatform-1.133.0.dist-info/WHEEL
google_cloud_aiplatform-1.133.0.dist-info/entry_points.txt
google_cloud_aiplatform-1.133.0.dist-info/namespace_packages.txt
google_cloud_aiplatform-1.133.0.dist-info/top_level.txt
google_cloud_aiplatform-1.133.0.dist-info/RECORD
