Metadata-Version: 2.4
Name: google-cloud-aiplatform
Version: 1.133.0
Summary: Vertex AI API client library
Home-page: https://github.com/googleapis/python-aiplatform
Author: Google LLC
Author-email: googleapis-packages@google.com
License: Apache 2.0
Platform: Posix; MacOS X; Windows
Classifier: Development Status :: 5 - Production/Stable
Classifier: Intended Audience :: Developers
Classifier: Operating System :: OS Independent
Classifier: Programming Language :: Python
Classifier: Programming Language :: Python :: 3
Classifier: Programming Language :: Python :: 3.9
Classifier: Programming Language :: Python :: 3.10
Classifier: Programming Language :: Python :: 3.11
Classifier: Programming Language :: Python :: 3.12
Classifier: Programming Language :: Python :: 3.13
Classifier: Programming Language :: Python :: 3.14
Classifier: Topic :: Internet
Classifier: Topic :: Software Development :: Libraries :: Python Modules
Requires-Python: >=3.9
License-File: LICENSE
Requires-Dist: google-api-core[grpc]!=2.0.*,!=2.1.*,!=2.2.*,!=2.3.*,!=2.4.*,!=2.5.*,!=2.6.*,!=2.7.*,<3.0.0,>=1.34.1
Requires-Dist: google-auth<3.0.0,>=2.47.0
Requires-Dist: proto-plus<2.0.0,>=1.22.3
Requires-Dist: protobuf!=4.21.0,!=4.21.1,!=4.21.2,!=4.21.3,!=4.21.4,!=4.21.5,<7.0.0,>=3.20.2
Requires-Dist: packaging>=14.3
Requires-Dist: google-cloud-storage<4.0.0,>=1.32.0; python_version < "3.13"
Requires-Dist: google-cloud-storage<4.0.0,>=2.10.0; python_version >= "3.13"
Requires-Dist: google-cloud-bigquery!=3.20.0,<4.0.0,>=1.15.0
Requires-Dist: google-cloud-resource-manager<3.0.0,>=1.3.3
Requires-Dist: google-genai<2.0.0,>=1.37.0
Requires-Dist: pydantic<3
Requires-Dist: typing_extensions
Requires-Dist: docstring_parser<1
Provides-Extra: endpoint
Requires-Dist: requests>=2.28.1; extra == "endpoint"
Requires-Dist: requests-toolbelt<=1.0.0; extra == "endpoint"
Provides-Extra: full
Requires-Dist: google-cloud-bigquery; extra == "full"
Requires-Dist: mlflow<=2.16.0,>=1.27.0; python_version < "3.13" and extra == "full"
Requires-Dist: tensorflow<3.0.0,>=2.3.0; python_version < "3.13" and extra == "full"
Requires-Dist: fastapi<=0.124.4,>=0.71.0; extra == "full"
Requires-Dist: jsonschema; extra == "full"
Requires-Dist: tensorflow<3.0.0,>=2.3.0; python_version < "3.13" and extra == "full"
Requires-Dist: requests-toolbelt<=1.0.0; extra == "full"
Requires-Dist: explainable-ai-sdk>=1.0.0; python_version < "3.13" and extra == "full"
Requires-Dist: pyarrow<8.0.0,>=3.0.0; python_version < "3.11" and extra == "full"
Requires-Dist: ray[default]!=2.10.*,!=2.11.*,!=2.12.*,!=2.13.*,!=2.14.*,!=2.15.*,!=2.16.*,!=2.17.*,!=2.18.*,!=2.19.*,!=2.20.*,!=2.21.*,!=2.22.*,!=2.23.*,!=2.24.*,!=2.25.*,!=2.26.*,!=2.27.*,!=2.28.*,!=2.29.*,!=2.30.*,!=2.31.*,!=2.32.*,!=2.34.*,!=2.35.*,!=2.36.*,!=2.37.*,!=2.38.*,!=2.39.*,!=2.40.*,!=2.41.*,!=2.5.*,!=2.6.*,!=2.7.*,!=2.8.*,!=2.9.0,!=2.9.1,!=2.9.2,<=2.42.0,>=2.4; python_version < "3.11" and extra == "full"
Requires-Dist: ruamel.yaml; extra == "full"
Requires-Dist: urllib3<1.27,>=1.21.1; extra == "full"
Requires-Dist: pyyaml<7,>=5.3.1; extra == "full"
Requires-Dist: scikit-learn<1.6.0; python_version <= "3.10" and extra == "full"
Requires-Dist: scikit-learn; python_version > "3.10" and extra == "full"
Requires-Dist: pyarrow>=14.0.0; python_version >= "3.12" and extra == "full"
Requires-Dist: google-vizier>=0.1.6; extra == "full"
Requires-Dist: requests>=2.28.1; extra == "full"
Requires-Dist: docker>=5.0.3; extra == "full"
Requires-Dist: pyyaml; extra == "full"
Requires-Dist: litellm!=1.77.2,!=1.77.3,!=1.77.4,>=1.72.4; extra == "full"
Requires-Dist: werkzeug<4.0.0,>=2.0.0; extra == "full"
Requires-Dist: tqdm>=4.23.0; extra == "full"
Requires-Dist: uvicorn[standard]>=0.16.0; extra == "full"
Requires-Dist: google-cloud-bigquery-storage; extra == "full"
Requires-Dist: tensorboard-plugin-profile<2.18.0,>=2.4.0; extra == "full"
Requires-Dist: pyarrow>=10.0.1; python_version == "3.11" and extra == "full"
Requires-Dist: lit-nlp==0.4.0; python_version < "3.13" and extra == "full"
Requires-Dist: pyarrow>=6.0.1; extra == "full"
Requires-Dist: mlflow>=1.27.0; python_version >= "3.13" and extra == "full"
Requires-Dist: ray[default]<=2.47.1,>=2.5; python_version == "3.11" and extra == "full"
Requires-Dist: pandas>=1.0.0; extra == "full"
Requires-Dist: numpy>=1.15.0; extra == "full"
Requires-Dist: httpx<=0.28.1,>=0.23.0; extra == "full"
Requires-Dist: starlette>=0.17.1; extra == "full"
Requires-Dist: immutabledict; extra == "full"
Provides-Extra: metadata
Requires-Dist: pandas>=1.0.0; extra == "metadata"
Requires-Dist: numpy>=1.15.0; extra == "metadata"
Provides-Extra: tensorboard
Requires-Dist: tensorboard-plugin-profile<2.18.0,>=2.4.0; extra == "tensorboard"
Requires-Dist: werkzeug<4.0.0,>=2.0.0; extra == "tensorboard"
Provides-Extra: testing
Requires-Dist: google-cloud-bigquery; extra == "testing"
Requires-Dist: mlflow<=2.16.0,>=1.27.0; python_version < "3.13" and extra == "testing"
Requires-Dist: tensorflow<3.0.0,>=2.3.0; python_version < "3.13" and extra == "testing"
Requires-Dist: fastapi<=0.124.4,>=0.71.0; extra == "testing"
Requires-Dist: jsonschema; extra == "testing"
Requires-Dist: tensorflow<3.0.0,>=2.3.0; python_version < "3.13" and extra == "testing"
Requires-Dist: requests-toolbelt<=1.0.0; extra == "testing"
Requires-Dist: explainable-ai-sdk>=1.0.0; python_version < "3.13" and extra == "testing"
Requires-Dist: pyarrow<8.0.0,>=3.0.0; python_version < "3.11" and extra == "testing"
Requires-Dist: ray[default]!=2.10.*,!=2.11.*,!=2.12.*,!=2.13.*,!=2.14.*,!=2.15.*,!=2.16.*,!=2.17.*,!=2.18.*,!=2.19.*,!=2.20.*,!=2.21.*,!=2.22.*,!=2.23.*,!=2.24.*,!=2.25.*,!=2.26.*,!=2.27.*,!=2.28.*,!=2.29.*,!=2.30.*,!=2.31.*,!=2.32.*,!=2.34.*,!=2.35.*,!=2.36.*,!=2.37.*,!=2.38.*,!=2.39.*,!=2.40.*,!=2.41.*,!=2.5.*,!=2.6.*,!=2.7.*,!=2.8.*,!=2.9.0,!=2.9.1,!=2.9.2,<=2.42.0,>=2.4; python_version < "3.11" and extra == "testing"
Requires-Dist: ruamel.yaml; extra == "testing"
Requires-Dist: urllib3<1.27,>=1.21.1; extra == "testing"
Requires-Dist: pyyaml<7,>=5.3.1; extra == "testing"
Requires-Dist: scikit-learn<1.6.0; python_version <= "3.10" and extra == "testing"
Requires-Dist: scikit-learn; python_version > "3.10" and extra == "testing"
Requires-Dist: pyarrow>=14.0.0; python_version >= "3.12" and extra == "testing"
Requires-Dist: google-vizier>=0.1.6; extra == "testing"
Requires-Dist: requests>=2.28.1; extra == "testing"
Requires-Dist: docker>=5.0.3; extra == "testing"
Requires-Dist: pyyaml; extra == "testing"
Requires-Dist: litellm!=1.77.2,!=1.77.3,!=1.77.4,>=1.72.4; extra == "testing"
Requires-Dist: werkzeug<4.0.0,>=2.0.0; extra == "testing"
Requires-Dist: tqdm>=4.23.0; extra == "testing"
Requires-Dist: uvicorn[standard]>=0.16.0; extra == "testing"
Requires-Dist: google-cloud-bigquery-storage; extra == "testing"
Requires-Dist: tensorboard-plugin-profile<2.18.0,>=2.4.0; extra == "testing"
Requires-Dist: pyarrow>=10.0.1; python_version == "3.11" and extra == "testing"
Requires-Dist: lit-nlp==0.4.0; python_version < "3.13" and extra == "testing"
Requires-Dist: pyarrow>=6.0.1; extra == "testing"
Requires-Dist: mlflow>=1.27.0; python_version >= "3.13" and extra == "testing"
Requires-Dist: ray[default]<=2.47.1,>=2.5; python_version == "3.11" and extra == "testing"
Requires-Dist: pandas>=1.0.0; extra == "testing"
Requires-Dist: numpy>=1.15.0; extra == "testing"
Requires-Dist: httpx<=0.28.1,>=0.23.0; extra == "testing"
Requires-Dist: starlette>=0.17.1; extra == "testing"
Requires-Dist: immutabledict; extra == "testing"
Requires-Dist: tensorboard-plugin-profile<2.18.0,>=2.4.0; extra == "testing"
Requires-Dist: werkzeug<4.0.0,>=2.0.0; extra == "testing"
Requires-Dist: sentencepiece>=0.2.0; extra == "testing"
Requires-Dist: nltk; extra == "testing"
Requires-Dist: google-vizier>=0.1.6; extra == "testing"
Requires-Dist: aiohttp; extra == "testing"
Requires-Dist: bigframes; (python_version >= "3.10" and python_version < "3.14") and extra == "testing"
Requires-Dist: google-api-core<3.0.0,>=2.11; extra == "testing"
Requires-Dist: grpcio-testing; extra == "testing"
Requires-Dist: grpcio-tools>=1.63.0; python_version >= "3.13" and extra == "testing"
Requires-Dist: ipython; extra == "testing"
Requires-Dist: kfp<3.0.0,>=2.6.0; python_version < "3.13" and extra == "testing"
Requires-Dist: pytest-asyncio; extra == "testing"
Requires-Dist: pytest-cov; extra == "testing"
Requires-Dist: mock; extra == "testing"
Requires-Dist: pytest-xdist; extra == "testing"
Requires-Dist: Pillow; extra == "testing"
Requires-Dist: scikit-learn<1.6.0; python_version <= "3.10" and extra == "testing"
Requires-Dist: scikit-learn; python_version > "3.10" and extra == "testing"
Requires-Dist: tensorflow==2.14.1; python_version <= "3.11" and extra == "testing"
Requires-Dist: tensorflow==2.19.0; (python_version > "3.11" and python_version < "3.13") and extra == "testing"
Requires-Dist: protobuf<=5.29.4; extra == "testing"
Requires-Dist: torch<2.1.0,>=2.0.0; python_version <= "3.11" and extra == "testing"
Requires-Dist: torch>=2.2.0; (python_version > "3.11" and python_version < "3.13") and extra == "testing"
Requires-Dist: requests-toolbelt<=1.0.0; extra == "testing"
Requires-Dist: immutabledict; extra == "testing"
Requires-Dist: xgboost; extra == "testing"
Provides-Extra: xai
Requires-Dist: tensorflow<3.0.0,>=2.3.0; python_version < "3.13" and extra == "xai"
Provides-Extra: lit
Requires-Dist: tensorflow<3.0.0,>=2.3.0; python_version < "3.13" and extra == "lit"
Requires-Dist: pandas>=1.0.0; extra == "lit"
Requires-Dist: lit-nlp==0.4.0; python_version < "3.13" and extra == "lit"
Requires-Dist: explainable-ai-sdk>=1.0.0; python_version < "3.13" and extra == "lit"
Provides-Extra: cloud-profiler
Requires-Dist: tensorboard-plugin-profile<2.18.0,>=2.4.0; extra == "cloud-profiler"
Requires-Dist: werkzeug<4.0.0,>=2.0.0; extra == "cloud-profiler"
Provides-Extra: pipelines
Requires-Dist: pyyaml<7,>=5.3.1; extra == "pipelines"
Provides-Extra: vizier
Requires-Dist: google-vizier>=0.1.6; extra == "vizier"
Provides-Extra: prediction
Requires-Dist: docker>=5.0.3; extra == "prediction"
Requires-Dist: fastapi<=0.124.4,>=0.71.0; extra == "prediction"
Requires-Dist: httpx<=0.28.1,>=0.23.0; extra == "prediction"
Requires-Dist: starlette>=0.17.1; extra == "prediction"
Requires-Dist: uvicorn[standard]>=0.16.0; extra == "prediction"
Provides-Extra: datasets
Requires-Dist: pyarrow<8.0.0,>=3.0.0; python_version < "3.11" and extra == "datasets"
Requires-Dist: pyarrow>=10.0.1; python_version == "3.11" and extra == "datasets"
Requires-Dist: pyarrow>=14.0.0; python_version >= "3.12" and extra == "datasets"
Provides-Extra: private-endpoints
Requires-Dist: urllib3<1.27,>=1.21.1; extra == "private-endpoints"
Requires-Dist: requests>=2.28.1; extra == "private-endpoints"
Provides-Extra: autologging
Requires-Dist: mlflow<=2.16.0,>=1.27.0; python_version < "3.13" and extra == "autologging"
Requires-Dist: mlflow>=1.27.0; python_version >= "3.13" and extra == "autologging"
Provides-Extra: preview
Provides-Extra: ray
Requires-Dist: ray[default]!=2.10.*,!=2.11.*,!=2.12.*,!=2.13.*,!=2.14.*,!=2.15.*,!=2.16.*,!=2.17.*,!=2.18.*,!=2.19.*,!=2.20.*,!=2.21.*,!=2.22.*,!=2.23.*,!=2.24.*,!=2.25.*,!=2.26.*,!=2.27.*,!=2.28.*,!=2.29.*,!=2.30.*,!=2.31.*,!=2.32.*,!=2.34.*,!=2.35.*,!=2.36.*,!=2.37.*,!=2.38.*,!=2.39.*,!=2.40.*,!=2.41.*,!=2.5.*,!=2.6.*,!=2.7.*,!=2.8.*,!=2.9.0,!=2.9.1,!=2.9.2,<=2.42.0,>=2.4; python_version < "3.11" and extra == "ray"
Requires-Dist: ray[default]<=2.47.1,>=2.5; python_version == "3.11" and extra == "ray"
Requires-Dist: google-cloud-bigquery-storage; extra == "ray"
Requires-Dist: google-cloud-bigquery; extra == "ray"
Requires-Dist: pandas>=1.0.0; extra == "ray"
Requires-Dist: pyarrow>=6.0.1; extra == "ray"
Requires-Dist: immutabledict; extra == "ray"
Provides-Extra: ray-testing
Requires-Dist: ray[default]!=2.10.*,!=2.11.*,!=2.12.*,!=2.13.*,!=2.14.*,!=2.15.*,!=2.16.*,!=2.17.*,!=2.18.*,!=2.19.*,!=2.20.*,!=2.21.*,!=2.22.*,!=2.23.*,!=2.24.*,!=2.25.*,!=2.26.*,!=2.27.*,!=2.28.*,!=2.29.*,!=2.30.*,!=2.31.*,!=2.32.*,!=2.34.*,!=2.35.*,!=2.36.*,!=2.37.*,!=2.38.*,!=2.39.*,!=2.40.*,!=2.41.*,!=2.5.*,!=2.6.*,!=2.7.*,!=2.8.*,!=2.9.0,!=2.9.1,!=2.9.2,<=2.42.0,>=2.4; python_version < "3.11" and extra == "ray-testing"
Requires-Dist: ray[default]<=2.47.1,>=2.5; python_version == "3.11" and extra == "ray-testing"
Requires-Dist: google-cloud-bigquery-storage; extra == "ray-testing"
Requires-Dist: google-cloud-bigquery; extra == "ray-testing"
Requires-Dist: pandas>=1.0.0; extra == "ray-testing"
Requires-Dist: pyarrow>=6.0.1; extra == "ray-testing"
Requires-Dist: immutabledict; extra == "ray-testing"
Requires-Dist: pytest-xdist; extra == "ray-testing"
Requires-Dist: ray[train]; extra == "ray-testing"
Requires-Dist: scikit-learn<1.6.0; extra == "ray-testing"
Requires-Dist: tensorflow; python_version < "3.13" and extra == "ray-testing"
Requires-Dist: torch<2.1.0,>=2.0.0; extra == "ray-testing"
Requires-Dist: xgboost; extra == "ray-testing"
Requires-Dist: xgboost_ray; extra == "ray-testing"
Provides-Extra: adk
Requires-Dist: google-adk<2.0.0,>=1.0.0; extra == "adk"
Requires-Dist: opentelemetry-instrumentation-google-genai<1.0.0,>=0.3b0; extra == "adk"
Provides-Extra: reasoningengine
Requires-Dist: cloudpickle<4.0,>=3.0; extra == "reasoningengine"
Requires-Dist: google-cloud-trace<2; extra == "reasoningengine"
Requires-Dist: opentelemetry-sdk<2; extra == "reasoningengine"
Requires-Dist: opentelemetry-exporter-gcp-logging<2.0.0,>=1.11.0a0; extra == "reasoningengine"
Requires-Dist: opentelemetry-exporter-gcp-trace<2; extra == "reasoningengine"
Requires-Dist: opentelemetry-exporter-otlp-proto-http<2; extra == "reasoningengine"
Requires-Dist: pydantic<3,>=2.11.1; extra == "reasoningengine"
Requires-Dist: typing_extensions; extra == "reasoningengine"
Provides-Extra: agent-engines
Requires-Dist: packaging>=24.0; extra == "agent-engines"
Requires-Dist: cloudpickle<4.0,>=3.0; extra == "agent-engines"
Requires-Dist: google-cloud-trace<2; extra == "agent-engines"
Requires-Dist: google-cloud-logging<4; extra == "agent-engines"
Requires-Dist: opentelemetry-sdk<2; extra == "agent-engines"
Requires-Dist: opentelemetry-exporter-gcp-logging<2.0.0,>=1.11.0a0; extra == "agent-engines"
Requires-Dist: opentelemetry-exporter-gcp-trace<2; extra == "agent-engines"
Requires-Dist: opentelemetry-exporter-otlp-proto-http<2; extra == "agent-engines"
Requires-Dist: pydantic<3,>=2.11.1; extra == "agent-engines"
Requires-Dist: typing_extensions; extra == "agent-engines"
Provides-Extra: evaluation
Requires-Dist: pandas>=1.0.0; extra == "evaluation"
Requires-Dist: tqdm>=4.23.0; extra == "evaluation"
Requires-Dist: scikit-learn<1.6.0; python_version <= "3.10" and extra == "evaluation"
Requires-Dist: scikit-learn; python_version > "3.10" and extra == "evaluation"
Requires-Dist: jsonschema; extra == "evaluation"
Requires-Dist: ruamel.yaml; extra == "evaluation"
Requires-Dist: pyyaml; extra == "evaluation"
Requires-Dist: litellm!=1.77.2,!=1.77.3,!=1.77.4,>=1.72.4; extra == "evaluation"
Provides-Extra: langchain
Requires-Dist: langchain<0.4,>=0.3; extra == "langchain"
Requires-Dist: langchain-core<0.4,>=0.3; extra == "langchain"
Requires-Dist: langchain-google-vertexai<3,>=2.0.22; extra == "langchain"
Requires-Dist: langgraph<0.4,>=0.2.45; extra == "langchain"
Requires-Dist: openinference-instrumentation-langchain<0.2,>=0.1.19; extra == "langchain"
Provides-Extra: langchain-testing
Requires-Dist: openinference-instrumentation-langchain<0.2,>=0.1.19; extra == "langchain-testing"
Requires-Dist: google-cloud-trace<2; extra == "langchain-testing"
Requires-Dist: typing_extensions; extra == "langchain-testing"
Requires-Dist: pytest-xdist; extra == "langchain-testing"
Requires-Dist: opentelemetry-exporter-otlp-proto-http<2; extra == "langchain-testing"
Requires-Dist: opentelemetry-exporter-gcp-trace<2; extra == "langchain-testing"
Requires-Dist: langchain-core<0.4,>=0.3; extra == "langchain-testing"
Requires-Dist: cloudpickle<4.0,>=3.0; extra == "langchain-testing"
Requires-Dist: langgraph<0.4,>=0.2.45; extra == "langchain-testing"
Requires-Dist: langchain-google-vertexai<3,>=2.0.22; extra == "langchain-testing"
Requires-Dist: opentelemetry-sdk<2; extra == "langchain-testing"
Requires-Dist: absl-py; extra == "langchain-testing"
Requires-Dist: opentelemetry-exporter-gcp-logging<2.0.0,>=1.11.0a0; extra == "langchain-testing"
Requires-Dist: langchain<0.4,>=0.3; extra == "langchain-testing"
Requires-Dist: pydantic<3,>=2.11.1; extra == "langchain-testing"
Provides-Extra: tokenization
Requires-Dist: sentencepiece>=0.2.0; extra == "tokenization"
Provides-Extra: ag2
Requires-Dist: ag2[gemini]; extra == "ag2"
Requires-Dist: openinference-instrumentation-autogen<0.2,>=0.1.6; extra == "ag2"
Provides-Extra: ag2-testing
Requires-Dist: google-cloud-trace<2; extra == "ag2-testing"
Requires-Dist: typing_extensions; extra == "ag2-testing"
Requires-Dist: pytest-xdist; extra == "ag2-testing"
Requires-Dist: opentelemetry-exporter-otlp-proto-http<2; extra == "ag2-testing"
Requires-Dist: opentelemetry-exporter-gcp-trace<2; extra == "ag2-testing"
Requires-Dist: cloudpickle<4.0,>=3.0; extra == "ag2-testing"
Requires-Dist: openinference-instrumentation-autogen<0.2,>=0.1.6; extra == "ag2-testing"
Requires-Dist: ag2[gemini]; extra == "ag2-testing"
Requires-Dist: opentelemetry-sdk<2; extra == "ag2-testing"
Requires-Dist: absl-py; extra == "ag2-testing"
Requires-Dist: opentelemetry-exporter-gcp-logging<2.0.0,>=1.11.0a0; extra == "ag2-testing"
Requires-Dist: pydantic<3,>=2.11.1; extra == "ag2-testing"
Provides-Extra: llama-index
Requires-Dist: llama-index; extra == "llama-index"
Requires-Dist: llama-index-llms-google-genai; extra == "llama-index"
Requires-Dist: openinference-instrumentation-llama-index<4.0,>=3.0; extra == "llama-index"
Provides-Extra: llama-index-testing
Requires-Dist: google-cloud-trace<2; extra == "llama-index-testing"
Requires-Dist: typing_extensions; extra == "llama-index-testing"
Requires-Dist: pytest-xdist; extra == "llama-index-testing"
Requires-Dist: opentelemetry-exporter-otlp-proto-http<2; extra == "llama-index-testing"
Requires-Dist: opentelemetry-exporter-gcp-trace<2; extra == "llama-index-testing"
Requires-Dist: llama-index; extra == "llama-index-testing"
Requires-Dist: cloudpickle<4.0,>=3.0; extra == "llama-index-testing"
Requires-Dist: llama-index-llms-google-genai; extra == "llama-index-testing"
Requires-Dist: opentelemetry-sdk<2; extra == "llama-index-testing"
Requires-Dist: absl-py; extra == "llama-index-testing"
Requires-Dist: opentelemetry-exporter-gcp-logging<2.0.0,>=1.11.0a0; extra == "llama-index-testing"
Requires-Dist: openinference-instrumentation-llama-index<4.0,>=3.0; extra == "llama-index-testing"
Requires-Dist: pydantic<3,>=2.11.1; extra == "llama-index-testing"
Dynamic: author
Dynamic: author-email
Dynamic: classifier
Dynamic: description
Dynamic: home-page
Dynamic: license
Dynamic: license-file
Dynamic: platform
Dynamic: provides-extra
Dynamic: requires-dist
Dynamic: requires-python
Dynamic: summary
